munud/__init__.py
munud/cgen.py
munud/cgen_types.py
munud/main.py
munud/munud.py
munud/munud_types.py
munud/utils.py
munud-0.3.1.dist-info/LICENSE
munud-0.3.1.dist-info/METADATA
munud-0.3.1.dist-info/WHEEL
munud-0.3.1.dist-info/entry_points.txt
munud-0.3.1.dist-info/RECORD
